diro_py-0.1.1.dist-info/METADATA
diro_py-0.1.1.dist-info/WHEEL
diro/__init__.py
diro/__init__.pyi
diro/py.typed
diro/diro.abi3.so
diro_py-0.1.1.dist-info/RECORD
