Metadata-Version: 2.1
Name: diro-py
Version: 0.1.1
Summary: A Dice expression parser
Author: abrahumlink
License: MIT
